{
  "project_info": {
    "project_number": "951852321963",
    "project_id": "raychatiing",
    "storage_bucket": "raychatiing.appspot.com"
  },
  "client": [
    {
      "client_info": {
        "mobilesdk_app_id": "1:951852321963:android:a6984d3ba0002cc83b7bee",
        "android_client_info": {
          "package_name": "com.example.chat_app"
        }
      },
      "oauth_client": [
        {
          "client_id": "951852321963-6vsm7fsbjnko384mdktt519moloq62vb.apps.googleusercontent.com",
          "client_type": 3
        }
      ],
      "api_key": [
        {
          "current_key": "AIzaSyD_taCdDGbd2VEAqounHVtqXO-HKJQuVs0"
        }
      ],
      "services": {
        "appinvite_service": {
          "other_platform_oauth_client": [
            {
              "client_id": "951852321963-6vsm7fsbjnko384mdktt519moloq62vb.apps.googleusercontent.com",
              "client_type": 3
            }
          ]
        }
      }
    },
    {
      "client_info": {
        "mobilesdk_app_id": "1:951852321963:android:c75b9a4c9427a2913b7bee",
        "android_client_info": {
          "package_name": "com.example.raychat_flutter_apprentice"
        }
      },
      "oauth_client": [
        {
          "client_id": "951852321963-6vsm7fsbjnko384mdktt519moloq62vb.apps.googleusercontent.com",
          "client_type": 3
        }
      ],
      "api_key": [
        {
          "current_key": "AIzaSyD_taCdDGbd2VEAqounHVtqXO-HKJQuVs0"
        }
      ],
      "services": {
        "appinvite_service": {
          "other_platform_oauth_client": [
            {
              "client_id": "951852321963-6vsm7fsbjnko384mdktt519moloq62vb.apps.googleusercontent.com",
              "client_type": 3
            }
          ]
        }
      }
    }
  ],
  "configuration_version": "1"
}